rlbot_flatbuffers-0.18.4.dist-info/METADATA
rlbot_flatbuffers-0.18.4.dist-info/WHEEL
rlbot_flatbuffers-0.18.4.dist-info/licenses/LICENSE
rlbot_flatbuffers/__init__.py
rlbot_flatbuffers/__init__.pyi
rlbot_flatbuffers/py.typed
rlbot_flatbuffers/rlbot_flatbuffers.pyd
rlbot_flatbuffers-0.18.4.dist-info/RECORD
