Metadata-Version: 2.4
Name: rlbot_flatbuffers
Version: 0.18.4
Classifier: Programming Language :: Rust
Classifier: Programming Language :: Python :: Implementation :: CPython
Classifier: Programming Language :: Python :: Implementation :: PyPy
License-File: LICENSE
Summary: A Python module implemented in Rust for serializing and deserializing RLBot's flatbuffers
Requires-Python: >=3.10
Project-URL: Source Code, https://github.com/RLBot/flatbuffers-python
